pibooth_lcd_i2c.py
pibooth_lcd_i2c-1.0.0.dist-info/LICENSE
pibooth_lcd_i2c-1.0.0.dist-info/METADATA
pibooth_lcd_i2c-1.0.0.dist-info/WHEEL
pibooth_lcd_i2c-1.0.0.dist-info/entry_points.txt
pibooth_lcd_i2c-1.0.0.dist-info/top_level.txt
pibooth_lcd_i2c-1.0.0.dist-info/zip-safe
pibooth_lcd_i2c-1.0.0.dist-info/RECORD
