Metadata-Version: 2.1
Name: pibooth-lcd-i2c
Version: 1.0.0
Summary: Plugin to handle small LCD display.
Home-page: https://github.com/DJ-Dingo/pibooth-lcd-I2c
Author: Kenneth Nicholas Jørgensen, Vincent Verdeil
License: GPLv3
Download-URL: https://github.com/DJ-Dingo/pibooth-lcd-I2c/archive/1.0.0.tar.gz
Keywords: Raspberry Pi,camera,photobooth,pygame,lcd
Platform: unix
Platform: linux
Classifier: Development Status :: 5 - Production/Stable
Classifier: Environment :: Plugins
Classifier: Intended Audience :: Developers
Classifier: Intended Audience :: End Users/Desktop
Classifier: License :: OSI Approved :: GNU Affero General Public License v3
Classifier: Natural Language :: English
Classifier: Operating System :: POSIX :: Linux
Classifier: Programming Language :: Python :: 3.6
Classifier: Programming Language :: Python :: 3.7
Classifier: Programming Language :: Python :: 3.8
Classifier: Programming Language :: Python :: 3.9
Classifier: Topic :: Multimedia :: Graphics :: Capture :: Digital Camera
Requires-Dist: pibooth (>=2.0.0)
Requires-Dist: RPLCD (>=1.3.0)
